wm_cli_src/__init__.py
wm_cli_src-0.1.0.dist-info/WHEEL
wm_cli_src-0.1.0.dist-info/METADATA
wm_cli_src-0.1.0.dist-info/RECORD
