Metadata-Version: 2.1
Name: wm-cli-src
Version: 0.1.0
Summary: 
Author: mohamedarzikiwm
Author-email: mohamed.a@wemaintain.com
Requires-Python: >=3.7,<4.0
Classifier: Programming Language :: Python :: 3
Classifier: Programming Language :: Python :: 3.7
Classifier: Programming Language :: Python :: 3.8
Classifier: Programming Language :: Python :: 3.9
Requires-Dist: click (==8.0.0)
